{
  "ChunkName": "@luatests/base_lib_unpack.lua",
  "FunctionPrototypes": [
    {
      "NumFixedParams": 0,
      "TakesVarArg": true,
      "MaxFrameSize": 11,
      "SourceLineStart": 0,
      "SourceLineEnd": 30,
      "HasChildPrototype": false,
      "UseFFI": false,
      "Bytecode": [
        {
          "OpCode": "TDUP",
          "OpData": [ 0, 0 ],
          "SourceLine": 1
        },
        {
          "OpCode": "GSET",
          "OpData": [ 0, 1 ],
          "SourceLine": 1
        },
        {
          "OpCode": "GGET",
          "OpData": [ 0, 2 ],
          "SourceLine": 3
        },
        {
          "OpCode": "GGET",
          "OpData": [ 4, 3 ],
          "SourceLine": 3
        },
        {
          "OpCode": "GGET",
          "OpData": [ 8, 1 ],
          "SourceLine": 3
        },
        {
          "OpCode": "CALL",
          "OpData": [ 4, 0, 2 ],
          "SourceLine": 3
        },
        {
          "OpCode": "CALLM",
          "OpData": [ 0, 1, 0 ],
          "SourceLine": 3
        },
        {
          "OpCode": "GGET",
          "OpData": [ 0, 2 ],
          "SourceLine": 4
        },
        {
          "OpCode": "GGET",
          "OpData": [ 4, 3 ],
          "SourceLine": 4
        },
        {
          "OpCode": "GGET",
          "OpData": [ 8, 1 ],
          "SourceLine": 4
        },
        {
          "OpCode": "KSHORT",
          "OpData": [ 9, 10 ],
          "SourceLine": 4
        },
        {
          "OpCode": "CALL",
          "OpData": [ 4, 0, 3 ],
          "SourceLine": 4
        },
        {
          "OpCode": "CALLM",
          "OpData": [ 0, 1, 0 ],
          "SourceLine": 4
        },
        {
          "OpCode": "GGET",
          "OpData": [ 0, 2 ],
          "SourceLine": 5
        },
        {
          "OpCode": "GGET",
          "OpData": [ 4, 3 ],
          "SourceLine": 5
        },
        {
          "OpCode": "GGET",
          "OpData": [ 8, 1 ],
          "SourceLine": 5
        },
        {
          "OpCode": "KSHORT",
          "OpData": [ 9, 2 ],
          "SourceLine": 5
        },
        {
          "OpCode": "CALL",
          "OpData": [ 4, 0, 3 ],
          "SourceLine": 5
        },
        {
          "OpCode": "CALLM",
          "OpData": [ 0, 1, 0 ],
          "SourceLine": 5
        },
        {
          "OpCode": "GGET",
          "OpData": [ 0, 2 ],
          "SourceLine": 6
        },
        {
          "OpCode": "GGET",
          "OpData": [ 4, 3 ],
          "SourceLine": 6
        },
        {
          "OpCode": "GGET",
          "OpData": [ 8, 1 ],
          "SourceLine": 6
        },
        {
          "OpCode": "KSHORT",
          "OpData": [ 9, -1 ],
          "SourceLine": 6
        },
        {
          "OpCode": "CALL",
          "OpData": [ 4, 0, 3 ],
          "SourceLine": 6
        },
        {
          "OpCode": "CALLM",
          "OpData": [ 0, 1, 0 ],
          "SourceLine": 6
        },
        {
          "OpCode": "GGET",
          "OpData": [ 0, 2 ],
          "SourceLine": 7
        },
        {
          "OpCode": "GGET",
          "OpData": [ 4, 3 ],
          "SourceLine": 7
        },
        {
          "OpCode": "GGET",
          "OpData": [ 8, 1 ],
          "SourceLine": 7
        },
        {
          "OpCode": "KSHORT",
          "OpData": [ 9, -10 ],
          "SourceLine": 7
        },
        {
          "OpCode": "CALL",
          "OpData": [ 4, 0, 3 ],
          "SourceLine": 7
        },
        {
          "OpCode": "CALLM",
          "OpData": [ 0, 1, 0 ],
          "SourceLine": 7
        },
        {
          "OpCode": "GGET",
          "OpData": [ 0, 2 ],
          "SourceLine": 8
        },
        {
          "OpCode": "GGET",
          "OpData": [ 4, 3 ],
          "SourceLine": 8
        },
        {
          "OpCode": "GGET",
          "OpData": [ 8, 1 ],
          "SourceLine": 8
        },
        {
          "OpCode": "KSHORT",
          "OpData": [ 9, 4 ],
          "SourceLine": 8
        },
        {
          "OpCode": "KSHORT",
          "OpData": [ 10, 3 ],
          "SourceLine": 8
        },
        {
          "OpCode": "CALL",
          "OpData": [ 4, 0, 4 ],
          "SourceLine": 8
        },
        {
          "OpCode": "CALLM",
          "OpData": [ 0, 1, 0 ],
          "SourceLine": 8
        },
        {
          "OpCode": "GGET",
          "OpData": [ 0, 2 ],
          "SourceLine": 9
        },
        {
          "OpCode": "GGET",
          "OpData": [ 4, 3 ],
          "SourceLine": 9
        },
        {
          "OpCode": "GGET",
          "OpData": [ 8, 1 ],
          "SourceLine": 9
        },
        {
          "OpCode": "KSHORT",
          "OpData": [ 9, 1 ],
          "SourceLine": 9
        },
        {
          "OpCode": "KSHORT",
          "OpData": [ 10, 2 ],
          "SourceLine": 9
        },
        {
          "OpCode": "CALL",
          "OpData": [ 4, 0, 4 ],
          "SourceLine": 9
        },
        {
          "OpCode": "CALLM",
          "OpData": [ 0, 1, 0 ],
          "SourceLine": 9
        },
        {
          "OpCode": "GGET",
          "OpData": [ 0, 2 ],
          "SourceLine": 10
        },
        {
          "OpCode": "GGET",
          "OpData": [ 4, 3 ],
          "SourceLine": 10
        },
        {
          "OpCode": "GGET",
          "OpData": [ 8, 1 ],
          "SourceLine": 10
        },
        {
          "OpCode": "KSHORT",
          "OpData": [ 9, 3 ],
          "SourceLine": 10
        },
        {
          "OpCode": "KSHORT",
          "OpData": [ 10, 4 ],
          "SourceLine": 10
        },
        {
          "OpCode": "CALL",
          "OpData": [ 4, 0, 4 ],
          "SourceLine": 10
        },
        {
          "OpCode": "CALLM",
          "OpData": [ 0, 1, 0 ],
          "SourceLine": 10
        },
        {
          "OpCode": "GGET",
          "OpData": [ 0, 2 ],
          "SourceLine": 11
        },
        {
          "OpCode": "GGET",
          "OpData": [ 4, 3 ],
          "SourceLine": 11
        },
        {
          "OpCode": "GGET",
          "OpData": [ 8, 1 ],
          "SourceLine": 11
        },
        {
          "OpCode": "KSHORT",
          "OpData": [ 9, 3 ],
          "SourceLine": 11
        },
        {
          "OpCode": "KSHORT",
          "OpData": [ 10, 8 ],
          "SourceLine": 11
        },
        {
          "OpCode": "CALL",
          "OpData": [ 4, 0, 4 ],
          "SourceLine": 11
        },
        {
          "OpCode": "CALLM",
          "OpData": [ 0, 1, 0 ],
          "SourceLine": 11
        },
        {
          "OpCode": "GGET",
          "OpData": [ 0, 2 ],
          "SourceLine": 12
        },
        {
          "OpCode": "GGET",
          "OpData": [ 4, 3 ],
          "SourceLine": 12
        },
        {
          "OpCode": "GGET",
          "OpData": [ 8, 1 ],
          "SourceLine": 12
        },
        {
          "OpCode": "KSHORT",
          "OpData": [ 9, 3 ],
          "SourceLine": 12
        },
        {
          "OpCode": "KSHORT",
          "OpData": [ 10, 20 ],
          "SourceLine": 12
        },
        {
          "OpCode": "CALL",
          "OpData": [ 4, 0, 4 ],
          "SourceLine": 12
        },
        {
          "OpCode": "CALLM",
          "OpData": [ 0, 1, 0 ],
          "SourceLine": 12
        },
        {
          "OpCode": "GGET",
          "OpData": [ 0, 2 ],
          "SourceLine": 13
        },
        {
          "OpCode": "GGET",
          "OpData": [ 4, 3 ],
          "SourceLine": 13
        },
        {
          "OpCode": "GGET",
          "OpData": [ 8, 1 ],
          "SourceLine": 13
        },
        {
          "OpCode": "KSHORT",
          "OpData": [ 9, -10 ],
          "SourceLine": 13
        },
        {
          "OpCode": "KSHORT",
          "OpData": [ 10, 10 ],
          "SourceLine": 13
        },
        {
          "OpCode": "CALL",
          "OpData": [ 4, 0, 4 ],
          "SourceLine": 13
        },
        {
          "OpCode": "CALLM",
          "OpData": [ 0, 1, 0 ],
          "SourceLine": 13
        },
        {
          "OpCode": "GGET",
          "OpData": [ 0, 2 ],
          "SourceLine": 14
        },
        {
          "OpCode": "GGET",
          "OpData": [ 4, 3 ],
          "SourceLine": 14
        },
        {
          "OpCode": "GGET",
          "OpData": [ 8, 1 ],
          "SourceLine": 14
        },
        {
          "OpCode": "KSHORT",
          "OpData": [ 9, -10 ],
          "SourceLine": 14
        },
        {
          "OpCode": "KSHORT",
          "OpData": [ 10, -5 ],
          "SourceLine": 14
        },
        {
          "OpCode": "CALL",
          "OpData": [ 4, 0, 4 ],
          "SourceLine": 14
        },
        {
          "OpCode": "CALLM",
          "OpData": [ 0, 1, 0 ],
          "SourceLine": 14
        },
        {
          "OpCode": "GGET",
          "OpData": [ 0, 2 ],
          "SourceLine": 15
        },
        {
          "OpCode": "GGET",
          "OpData": [ 4, 3 ],
          "SourceLine": 15
        },
        {
          "OpCode": "GGET",
          "OpData": [ 8, 1 ],
          "SourceLine": 15
        },
        {
          "OpCode": "KSHORT",
          "OpData": [ 9, 10 ],
          "SourceLine": 15
        },
        {
          "OpCode": "KSHORT",
          "OpData": [ 10, 20 ],
          "SourceLine": 15
        },
        {
          "OpCode": "CALL",
          "OpData": [ 4, 0, 4 ],
          "SourceLine": 15
        },
        {
          "OpCode": "CALLM",
          "OpData": [ 0, 1, 0 ],
          "SourceLine": 15
        },
        {
          "OpCode": "GGET",
          "OpData": [ 0, 2 ],
          "SourceLine": 16
        },
        {
          "OpCode": "GGET",
          "OpData": [ 4, 3 ],
          "SourceLine": 16
        },
        {
          "OpCode": "GGET",
          "OpData": [ 8, 1 ],
          "SourceLine": 16
        },
        {
          "OpCode": "KSHORT",
          "OpData": [ 9, -3 ],
          "SourceLine": 16
        },
        {
          "OpCode": "KSHORT",
          "OpData": [ 10, 1 ],
          "SourceLine": 16
        },
        {
          "OpCode": "CALL",
          "OpData": [ 4, 0, 4 ],
          "SourceLine": 16
        },
        {
          "OpCode": "CALLM",
          "OpData": [ 0, 1, 0 ],
          "SourceLine": 16
        },
        {
          "OpCode": "GGET",
          "OpData": [ 0, 2 ],
          "SourceLine": 17
        },
        {
          "OpCode": "GGET",
          "OpData": [ 4, 3 ],
          "SourceLine": 17
        },
        {
          "OpCode": "GGET",
          "OpData": [ 8, 1 ],
          "SourceLine": 17
        },
        {
          "OpCode": "KSHORT",
          "OpData": [ 9, -3 ],
          "SourceLine": 17
        },
        {
          "OpCode": "KSHORT",
          "OpData": [ 10, 2 ],
          "SourceLine": 17
        },
        {
          "OpCode": "CALL",
          "OpData": [ 4, 0, 4 ],
          "SourceLine": 17
        },
        {
          "OpCode": "CALLM",
          "OpData": [ 0, 1, 0 ],
          "SourceLine": 17
        },
        {
          "OpCode": "GGET",
          "OpData": [ 0, 2 ],
          "SourceLine": 18
        },
        {
          "OpCode": "GGET",
          "OpData": [ 4, 3 ],
          "SourceLine": 18
        },
        {
          "OpCode": "GGET",
          "OpData": [ 8, 1 ],
          "SourceLine": 18
        },
        {
          "OpCode": "KSHORT",
          "OpData": [ 9, 7 ],
          "SourceLine": 18
        },
        {
          "OpCode": "KSHORT",
          "OpData": [ 10, 8 ],
          "SourceLine": 18
        },
        {
          "OpCode": "CALL",
          "OpData": [ 4, 0, 4 ],
          "SourceLine": 18
        },
        {
          "OpCode": "CALLM",
          "OpData": [ 0, 1, 0 ],
          "SourceLine": 18
        },
        {
          "OpCode": "GGET",
          "OpData": [ 0, 2 ],
          "SourceLine": 19
        },
        {
          "OpCode": "GGET",
          "OpData": [ 4, 3 ],
          "SourceLine": 19
        },
        {
          "OpCode": "GGET",
          "OpData": [ 8, 1 ],
          "SourceLine": 19
        },
        {
          "OpCode": "KSHORT",
          "OpData": [ 9, 6 ],
          "SourceLine": 19
        },
        {
          "OpCode": "KSHORT",
          "OpData": [ 10, 9 ],
          "SourceLine": 19
        },
        {
          "OpCode": "CALL",
          "OpData": [ 4, 0, 4 ],
          "SourceLine": 19
        },
        {
          "OpCode": "CALLM",
          "OpData": [ 0, 1, 0 ],
          "SourceLine": 19
        },
        {
          "OpCode": "GGET",
          "OpData": [ 0, 2 ],
          "SourceLine": 20
        },
        {
          "OpCode": "GGET",
          "OpData": [ 4, 3 ],
          "SourceLine": 20
        },
        {
          "OpCode": "GGET",
          "OpData": [ 8, 1 ],
          "SourceLine": 20
        },
        {
          "OpCode": "KSHORT",
          "OpData": [ 9, 4 ],
          "SourceLine": 20
        },
        {
          "OpCode": "KSHORT",
          "OpData": [ 10, 7 ],
          "SourceLine": 20
        },
        {
          "OpCode": "CALL",
          "OpData": [ 4, 0, 4 ],
          "SourceLine": 20
        },
        {
          "OpCode": "CALLM",
          "OpData": [ 0, 1, 0 ],
          "SourceLine": 20
        },
        {
          "OpCode": "GGET",
          "OpData": [ 0, 2 ],
          "SourceLine": 21
        },
        {
          "OpCode": "GGET",
          "OpData": [ 4, 3 ],
          "SourceLine": 21
        },
        {
          "OpCode": "GGET",
          "OpData": [ 8, 1 ],
          "SourceLine": 21
        },
        {
          "OpCode": "KSHORT",
          "OpData": [ 9, 1 ],
          "SourceLine": 21
        },
        {
          "OpCode": "KSHORT",
          "OpData": [ 10, 3 ],
          "SourceLine": 21
        },
        {
          "OpCode": "CALL",
          "OpData": [ 4, 0, 4 ],
          "SourceLine": 21
        },
        {
          "OpCode": "CALLM",
          "OpData": [ 0, 1, 0 ],
          "SourceLine": 21
        },
        {
          "OpCode": "TDUP",
          "OpData": [ 0, 4 ],
          "SourceLine": 23
        },
        {
          "OpCode": "GSET",
          "OpData": [ 0, 5 ],
          "SourceLine": 23
        },
        {
          "OpCode": "GGET",
          "OpData": [ 0, 2 ],
          "SourceLine": 25
        },
        {
          "OpCode": "GGET",
          "OpData": [ 4, 3 ],
          "SourceLine": 25
        },
        {
          "OpCode": "GGET",
          "OpData": [ 8, 5 ],
          "SourceLine": 25
        },
        {
          "OpCode": "KSHORT",
          "OpData": [ 9, 1 ],
          "SourceLine": 25
        },
        {
          "OpCode": "KSHORT",
          "OpData": [ 10, 2 ],
          "SourceLine": 25
        },
        {
          "OpCode": "CALL",
          "OpData": [ 4, 0, 4 ],
          "SourceLine": 25
        },
        {
          "OpCode": "CALLM",
          "OpData": [ 0, 1, 0 ],
          "SourceLine": 25
        },
        {
          "OpCode": "GGET",
          "OpData": [ 0, 2 ],
          "SourceLine": 26
        },
        {
          "OpCode": "GGET",
          "OpData": [ 4, 3 ],
          "SourceLine": 26
        },
        {
          "OpCode": "GGET",
          "OpData": [ 8, 5 ],
          "SourceLine": 26
        },
        {
          "OpCode": "KSHORT",
          "OpData": [ 9, -2 ],
          "SourceLine": 26
        },
        {
          "OpCode": "KSHORT",
          "OpData": [ 10, 2 ],
          "SourceLine": 26
        },
        {
          "OpCode": "CALL",
          "OpData": [ 4, 0, 4 ],
          "SourceLine": 26
        },
        {
          "OpCode": "CALLM",
          "OpData": [ 0, 1, 0 ],
          "SourceLine": 26
        },
        {
          "OpCode": "GGET",
          "OpData": [ 0, 2 ],
          "SourceLine": 27
        },
        {
          "OpCode": "GGET",
          "OpData": [ 4, 3 ],
          "SourceLine": 27
        },
        {
          "OpCode": "GGET",
          "OpData": [ 8, 5 ],
          "SourceLine": 27
        },
        {
          "OpCode": "KSHORT",
          "OpData": [ 9, -2 ],
          "SourceLine": 27
        },
        {
          "OpCode": "KSHORT",
          "OpData": [ 10, 4 ],
          "SourceLine": 27
        },
        {
          "OpCode": "CALL",
          "OpData": [ 4, 0, 4 ],
          "SourceLine": 27
        },
        {
          "OpCode": "CALLM",
          "OpData": [ 0, 1, 0 ],
          "SourceLine": 27
        },
        {
          "OpCode": "GGET",
          "OpData": [ 0, 2 ],
          "SourceLine": 28
        },
        {
          "OpCode": "GGET",
          "OpData": [ 4, 3 ],
          "SourceLine": 28
        },
        {
          "OpCode": "GGET",
          "OpData": [ 8, 5 ],
          "SourceLine": 28
        },
        {
          "OpCode": "KNUM",
          "OpData": [ 9, 0 ],
          "SourceLine": 28
        },
        {
          "OpCode": "KNUM",
          "OpData": [ 10, 1 ],
          "SourceLine": 28
        },
        {
          "OpCode": "CALL",
          "OpData": [ 4, 0, 4 ],
          "SourceLine": 28
        },
        {
          "OpCode": "CALLM",
          "OpData": [ 0, 1, 0 ],
          "SourceLine": 28
        },
        {
          "OpCode": "RET0",
          "OpData": [ 0, 1 ],
          "SourceLine": 28
        }
      ],
      "Upvalues": [],
      "ObjectConstants": [
        {
          "Type": "Table",
          "Value": [
            {
              "EntryKey": {
                "Type": "Int32",
                "Value": 1
              },
              "EntryValue": {
                "Type": "String",
                "Value": "a"
              }
            },
            {
              "EntryKey": {
                "Type": "Int32",
                "Value": 2
              },
              "EntryValue": {
                "Type": "String",
                "Value": "b"
              }
            },
            {
              "EntryKey": {
                "Type": "Int32",
                "Value": 3
              },
              "EntryValue": {
                "Type": "String",
                "Value": "c"
              }
            },
            {
              "EntryKey": {
                "Type": "Int32",
                "Value": 4
              },
              "EntryValue": {
                "Type": "String",
                "Value": "d"
              }
            },
            {
              "EntryKey": {
                "Type": "Int32",
                "Value": 5
              },
              "EntryValue": {
                "Type": "String",
                "Value": "e"
              }
            },
            {
              "EntryKey": {
                "Type": "Int32",
                "Value": 6
              },
              "EntryValue": {
                "Type": "String",
                "Value": "f"
              }
            },
            {
              "EntryKey": {
                "Type": "Int32",
                "Value": 7
              },
              "EntryValue": {
                "Type": "String",
                "Value": "g"
              }
            }
          ],
          "AdditionalNamedKeys": 0,
          "ArraySizeHint": 8
        },
        {
          "Type": "String",
          "Value": "t1"
        },
        {
          "Type": "String",
          "Value": "print"
        },
        {
          "Type": "String",
          "Value": "unpack"
        },
        {
          "Type": "Table",
          "Value": [
            {
              "EntryKey": {
                "Type": "Int32",
                "Value": 0
              },
              "EntryValue": {
                "Type": "String",
                "Value": "b"
              }
            },
            {
              "EntryKey": {
                "Type": "Int32",
                "Value": 1
              },
              "EntryValue": {
                "Type": "String",
                "Value": "c"
              }
            },
            {
              "EntryKey": {
                "Type": "Int32",
                "Value": 2
              },
              "EntryValue": {
                "Type": "String",
                "Value": "d"
              }
            },
            {
              "EntryKey": {
                "Type": "Int32",
                "Value": 100001
              },
              "EntryValue": {
                "Type": "String",
                "Value": "g"
              }
            },
            {
              "EntryKey": {
                "Type": "Int32",
                "Value": 10
              },
              "EntryValue": {
                "Type": "String",
                "Value": "e"
              }
            },
            {
              "EntryKey": {
                "Type": "Int32",
                "Value": -1
              },
              "EntryValue": {
                "Type": "String",
                "Value": "a"
              }
            },
            {
              "EntryKey": {
                "Type": "Int32",
                "Value": 100000
              },
              "EntryValue": {
                "Type": "String",
                "Value": "f"
              }
            }
          ],
          "AdditionalNamedKeys": 0,
          "ArraySizeHint": 3
        },
        {
          "Type": "String",
          "Value": "t2"
        }
      ],
      "NumberConstants": [
        {
          "Type": "Int32",
          "Value": 99999
        },
        {
          "Type": "Int32",
          "Value": 100002
        }
      ]
    }
  ]
}
