{
  "ChunkName": "@luatests/table_dup2.lua",
  "FunctionPrototypes": [
    {
      "NumFixedParams": 0,
      "TakesVarArg": false,
      "MaxFrameSize": 1,
      "SourceLineStart": 1,
      "SourceLineEnd": 12,
      "HasChildPrototype": false,
      "UseFFI": false,
      "Bytecode": [
        {
          "OpCode": "TDUP",
          "OpData": [ 0, 0 ],
          "SourceLine": 2
        },
        {
          "OpCode": "RET1",
          "OpData": [ 0, 2 ],
          "SourceLine": 11
        }
      ],
      "Upvalues": [],
      "ObjectConstants": [
        {
          "Type": "Table",
          "Value": [
            {
              "EntryKey": {
                "Type": "Int32",
                "Value": 1
              },
              "EntryValue": {
                "Type": "Int32",
                "Value": 301
              }
            },
            {
              "EntryKey": {
                "Type": "String",
                "Value": "a4"
              },
              "EntryValue": {
                "Type": "Int32",
                "Value": 4
              }
            },
            {
              "EntryKey": {
                "Type": "String",
                "Value": "a3"
              },
              "EntryValue": {
                "Type": "Int32",
                "Value": 3
              }
            },
            {
              "EntryKey": {
                "Type": "String",
                "Value": "a2"
              },
              "EntryValue": {
                "Type": "Int32",
                "Value": 2
              }
            },
            {
              "EntryKey": {
                "Type": "String",
                "Value": "a1"
              },
              "EntryValue": {
                "Type": "Int32",
                "Value": 1
              }
            },
            {
              "EntryKey": {
                "Type": "String",
                "Value": "a0"
              },
              "EntryValue": {
                "Type": "Int32",
                "Value": 0
              }
            },
            {
              "EntryKey": {
                "Type": "Int32",
                "Value": 2
              },
              "EntryValue": {
                "Type": "Int32",
                "Value": 302
              }
            },
            {
              "EntryKey": {
                "Type": "Int32",
                "Value": 3
              },
              "EntryValue": {
                "Type": "Int32",
                "Value": 303
              }
            }
          ],
          "AdditionalNamedKeys": 0,
          "ArraySizeHint": 0
        }
      ],
      "NumberConstants": []
    },
    {
      "NumFixedParams": 0,
      "TakesVarArg": true,
      "MaxFrameSize": 16,
      "SourceLineStart": 0,
      "SourceLineEnd": 25,
      "HasChildPrototype": true,
      "UseFFI": false,
      "Bytecode": [
        {
          "OpCode": "FNEW",
          "OpData": [ 0, 0 ],
          "SourceLine": 12
        },
        {
          "OpCode": "GSET",
          "OpData": [ 0, 1 ],
          "SourceLine": 1
        },
        {
          "OpCode": "GGET",
          "OpData": [ 0, 1 ],
          "SourceLine": 14
        },
        {
          "OpCode": "CALL",
          "OpData": [ 0, 2, 1 ],
          "SourceLine": 14
        },
        {
          "OpCode": "GSET",
          "OpData": [ 0, 2 ],
          "SourceLine": 14
        },
        {
          "OpCode": "GGET",
          "OpData": [ 0, 3 ],
          "SourceLine": 15
        },
        {
          "OpCode": "GGET",
          "OpData": [ 4, 2 ],
          "SourceLine": 15
        },
        {
          "OpCode": "TGETS",
          "OpData": [ 4, 4, 4 ],
          "SourceLine": 15
        },
        {
          "OpCode": "GGET",
          "OpData": [ 5, 2 ],
          "SourceLine": 15
        },
        {
          "OpCode": "TGETS",
          "OpData": [ 5, 5, 5 ],
          "SourceLine": 15
        },
        {
          "OpCode": "GGET",
          "OpData": [ 6, 2 ],
          "SourceLine": 15
        },
        {
          "OpCode": "TGETS",
          "OpData": [ 6, 6, 6 ],
          "SourceLine": 15
        },
        {
          "OpCode": "GGET",
          "OpData": [ 7, 2 ],
          "SourceLine": 15
        },
        {
          "OpCode": "TGETS",
          "OpData": [ 7, 7, 7 ],
          "SourceLine": 15
        },
        {
          "OpCode": "GGET",
          "OpData": [ 8, 2 ],
          "SourceLine": 15
        },
        {
          "OpCode": "TGETS",
          "OpData": [ 8, 8, 8 ],
          "SourceLine": 15
        },
        {
          "OpCode": "GGET",
          "OpData": [ 9, 2 ],
          "SourceLine": 15
        },
        {
          "OpCode": "TGETS",
          "OpData": [ 9, 9, 9 ],
          "SourceLine": 15
        },
        {
          "OpCode": "GGET",
          "OpData": [ 10, 2 ],
          "SourceLine": 15
        },
        {
          "OpCode": "TGETB",
          "OpData": [ 10, 10, 0 ],
          "SourceLine": 15
        },
        {
          "OpCode": "GGET",
          "OpData": [ 11, 2 ],
          "SourceLine": 15
        },
        {
          "OpCode": "KSHORT",
          "OpData": [ 12, -1 ],
          "SourceLine": 15
        },
        {
          "OpCode": "TGETV",
          "OpData": [ 11, 11, 12 ],
          "SourceLine": 15
        },
        {
          "OpCode": "GGET",
          "OpData": [ 12, 2 ],
          "SourceLine": 15
        },
        {
          "OpCode": "TGETB",
          "OpData": [ 12, 12, 1 ],
          "SourceLine": 15
        },
        {
          "OpCode": "GGET",
          "OpData": [ 13, 2 ],
          "SourceLine": 15
        },
        {
          "OpCode": "TGETB",
          "OpData": [ 13, 13, 2 ],
          "SourceLine": 15
        },
        {
          "OpCode": "GGET",
          "OpData": [ 14, 2 ],
          "SourceLine": 15
        },
        {
          "OpCode": "TGETB",
          "OpData": [ 14, 14, 3 ],
          "SourceLine": 15
        },
        {
          "OpCode": "GGET",
          "OpData": [ 15, 2 ],
          "SourceLine": 15
        },
        {
          "OpCode": "TGETB",
          "OpData": [ 15, 15, 4 ],
          "SourceLine": 15
        },
        {
          "OpCode": "CALL",
          "OpData": [ 0, 1, 13 ],
          "SourceLine": 15
        },
        {
          "OpCode": "GGET",
          "OpData": [ 0, 2 ],
          "SourceLine": 16
        },
        {
          "OpCode": "GGET",
          "OpData": [ 1, 2 ],
          "SourceLine": 16
        },
        {
          "OpCode": "TGETS",
          "OpData": [ 1, 1, 4 ],
          "SourceLine": 16
        },
        {
          "OpCode": "ADDVN",
          "OpData": [ 1, 1, 0 ],
          "SourceLine": 16
        },
        {
          "OpCode": "TSETS",
          "OpData": [ 1, 0, 4 ],
          "SourceLine": 16
        },
        {
          "OpCode": "GGET",
          "OpData": [ 0, 2 ],
          "SourceLine": 17
        },
        {
          "OpCode": "GGET",
          "OpData": [ 1, 2 ],
          "SourceLine": 17
        },
        {
          "OpCode": "TGETB",
          "OpData": [ 1, 1, 1 ],
          "SourceLine": 17
        },
        {
          "OpCode": "ADDVN",
          "OpData": [ 1, 1, 0 ],
          "SourceLine": 17
        },
        {
          "OpCode": "TSETB",
          "OpData": [ 1, 0, 1 ],
          "SourceLine": 17
        },
        {
          "OpCode": "GGET",
          "OpData": [ 0, 3 ],
          "SourceLine": 18
        },
        {
          "OpCode": "GGET",
          "OpData": [ 4, 2 ],
          "SourceLine": 18
        },
        {
          "OpCode": "TGETS",
          "OpData": [ 4, 4, 4 ],
          "SourceLine": 18
        },
        {
          "OpCode": "GGET",
          "OpData": [ 5, 2 ],
          "SourceLine": 18
        },
        {
          "OpCode": "TGETS",
          "OpData": [ 5, 5, 5 ],
          "SourceLine": 18
        },
        {
          "OpCode": "GGET",
          "OpData": [ 6, 2 ],
          "SourceLine": 18
        },
        {
          "OpCode": "TGETS",
          "OpData": [ 6, 6, 6 ],
          "SourceLine": 18
        },
        {
          "OpCode": "GGET",
          "OpData": [ 7, 2 ],
          "SourceLine": 18
        },
        {
          "OpCode": "TGETS",
          "OpData": [ 7, 7, 7 ],
          "SourceLine": 18
        },
        {
          "OpCode": "GGET",
          "OpData": [ 8, 2 ],
          "SourceLine": 18
        },
        {
          "OpCode": "TGETS",
          "OpData": [ 8, 8, 8 ],
          "SourceLine": 18
        },
        {
          "OpCode": "GGET",
          "OpData": [ 9, 2 ],
          "SourceLine": 18
        },
        {
          "OpCode": "TGETS",
          "OpData": [ 9, 9, 9 ],
          "SourceLine": 18
        },
        {
          "OpCode": "GGET",
          "OpData": [ 10, 2 ],
          "SourceLine": 18
        },
        {
          "OpCode": "TGETB",
          "OpData": [ 10, 10, 0 ],
          "SourceLine": 18
        },
        {
          "OpCode": "GGET",
          "OpData": [ 11, 2 ],
          "SourceLine": 18
        },
        {
          "OpCode": "KSHORT",
          "OpData": [ 12, -1 ],
          "SourceLine": 18
        },
        {
          "OpCode": "TGETV",
          "OpData": [ 11, 11, 12 ],
          "SourceLine": 18
        },
        {
          "OpCode": "GGET",
          "OpData": [ 12, 2 ],
          "SourceLine": 18
        },
        {
          "OpCode": "TGETB",
          "OpData": [ 12, 12, 1 ],
          "SourceLine": 18
        },
        {
          "OpCode": "GGET",
          "OpData": [ 13, 2 ],
          "SourceLine": 18
        },
        {
          "OpCode": "TGETB",
          "OpData": [ 13, 13, 2 ],
          "SourceLine": 18
        },
        {
          "OpCode": "GGET",
          "OpData": [ 14, 2 ],
          "SourceLine": 18
        },
        {
          "OpCode": "TGETB",
          "OpData": [ 14, 14, 3 ],
          "SourceLine": 18
        },
        {
          "OpCode": "GGET",
          "OpData": [ 15, 2 ],
          "SourceLine": 18
        },
        {
          "OpCode": "TGETB",
          "OpData": [ 15, 15, 4 ],
          "SourceLine": 18
        },
        {
          "OpCode": "CALL",
          "OpData": [ 0, 1, 13 ],
          "SourceLine": 18
        },
        {
          "OpCode": "GGET",
          "OpData": [ 0, 1 ],
          "SourceLine": 20
        },
        {
          "OpCode": "CALL",
          "OpData": [ 0, 2, 1 ],
          "SourceLine": 20
        },
        {
          "OpCode": "GSET",
          "OpData": [ 0, 10 ],
          "SourceLine": 20
        },
        {
          "OpCode": "GGET",
          "OpData": [ 0, 3 ],
          "SourceLine": 21
        },
        {
          "OpCode": "GGET",
          "OpData": [ 4, 10 ],
          "SourceLine": 21
        },
        {
          "OpCode": "TGETS",
          "OpData": [ 4, 4, 4 ],
          "SourceLine": 21
        },
        {
          "OpCode": "GGET",
          "OpData": [ 5, 10 ],
          "SourceLine": 21
        },
        {
          "OpCode": "TGETS",
          "OpData": [ 5, 5, 5 ],
          "SourceLine": 21
        },
        {
          "OpCode": "GGET",
          "OpData": [ 6, 10 ],
          "SourceLine": 21
        },
        {
          "OpCode": "TGETS",
          "OpData": [ 6, 6, 6 ],
          "SourceLine": 21
        },
        {
          "OpCode": "GGET",
          "OpData": [ 7, 10 ],
          "SourceLine": 21
        },
        {
          "OpCode": "TGETS",
          "OpData": [ 7, 7, 7 ],
          "SourceLine": 21
        },
        {
          "OpCode": "GGET",
          "OpData": [ 8, 10 ],
          "SourceLine": 21
        },
        {
          "OpCode": "TGETS",
          "OpData": [ 8, 8, 8 ],
          "SourceLine": 21
        },
        {
          "OpCode": "GGET",
          "OpData": [ 9, 10 ],
          "SourceLine": 21
        },
        {
          "OpCode": "TGETS",
          "OpData": [ 9, 9, 9 ],
          "SourceLine": 21
        },
        {
          "OpCode": "GGET",
          "OpData": [ 10, 10 ],
          "SourceLine": 21
        },
        {
          "OpCode": "TGETB",
          "OpData": [ 10, 10, 0 ],
          "SourceLine": 21
        },
        {
          "OpCode": "GGET",
          "OpData": [ 11, 10 ],
          "SourceLine": 21
        },
        {
          "OpCode": "KSHORT",
          "OpData": [ 12, -1 ],
          "SourceLine": 21
        },
        {
          "OpCode": "TGETV",
          "OpData": [ 11, 11, 12 ],
          "SourceLine": 21
        },
        {
          "OpCode": "GGET",
          "OpData": [ 12, 10 ],
          "SourceLine": 21
        },
        {
          "OpCode": "TGETB",
          "OpData": [ 12, 12, 1 ],
          "SourceLine": 21
        },
        {
          "OpCode": "GGET",
          "OpData": [ 13, 10 ],
          "SourceLine": 21
        },
        {
          "OpCode": "TGETB",
          "OpData": [ 13, 13, 2 ],
          "SourceLine": 21
        },
        {
          "OpCode": "GGET",
          "OpData": [ 14, 10 ],
          "SourceLine": 21
        },
        {
          "OpCode": "TGETB",
          "OpData": [ 14, 14, 3 ],
          "SourceLine": 21
        },
        {
          "OpCode": "GGET",
          "OpData": [ 15, 10 ],
          "SourceLine": 21
        },
        {
          "OpCode": "TGETB",
          "OpData": [ 15, 15, 4 ],
          "SourceLine": 21
        },
        {
          "OpCode": "CALL",
          "OpData": [ 0, 1, 13 ],
          "SourceLine": 21
        },
        {
          "OpCode": "GGET",
          "OpData": [ 0, 3 ],
          "SourceLine": 23
        },
        {
          "OpCode": "GGET",
          "OpData": [ 4, 2 ],
          "SourceLine": 23
        },
        {
          "OpCode": "TGETS",
          "OpData": [ 4, 4, 4 ],
          "SourceLine": 23
        },
        {
          "OpCode": "GGET",
          "OpData": [ 5, 2 ],
          "SourceLine": 23
        },
        {
          "OpCode": "TGETS",
          "OpData": [ 5, 5, 5 ],
          "SourceLine": 23
        },
        {
          "OpCode": "GGET",
          "OpData": [ 6, 2 ],
          "SourceLine": 23
        },
        {
          "OpCode": "TGETS",
          "OpData": [ 6, 6, 6 ],
          "SourceLine": 23
        },
        {
          "OpCode": "GGET",
          "OpData": [ 7, 2 ],
          "SourceLine": 23
        },
        {
          "OpCode": "TGETS",
          "OpData": [ 7, 7, 7 ],
          "SourceLine": 23
        },
        {
          "OpCode": "GGET",
          "OpData": [ 8, 2 ],
          "SourceLine": 23
        },
        {
          "OpCode": "TGETS",
          "OpData": [ 8, 8, 8 ],
          "SourceLine": 23
        },
        {
          "OpCode": "GGET",
          "OpData": [ 9, 2 ],
          "SourceLine": 23
        },
        {
          "OpCode": "TGETS",
          "OpData": [ 9, 9, 9 ],
          "SourceLine": 23
        },
        {
          "OpCode": "GGET",
          "OpData": [ 10, 2 ],
          "SourceLine": 23
        },
        {
          "OpCode": "TGETB",
          "OpData": [ 10, 10, 0 ],
          "SourceLine": 23
        },
        {
          "OpCode": "GGET",
          "OpData": [ 11, 2 ],
          "SourceLine": 23
        },
        {
          "OpCode": "KSHORT",
          "OpData": [ 12, -1 ],
          "SourceLine": 23
        },
        {
          "OpCode": "TGETV",
          "OpData": [ 11, 11, 12 ],
          "SourceLine": 23
        },
        {
          "OpCode": "GGET",
          "OpData": [ 12, 2 ],
          "SourceLine": 23
        },
        {
          "OpCode": "TGETB",
          "OpData": [ 12, 12, 1 ],
          "SourceLine": 23
        },
        {
          "OpCode": "GGET",
          "OpData": [ 13, 2 ],
          "SourceLine": 23
        },
        {
          "OpCode": "TGETB",
          "OpData": [ 13, 13, 2 ],
          "SourceLine": 23
        },
        {
          "OpCode": "GGET",
          "OpData": [ 14, 2 ],
          "SourceLine": 23
        },
        {
          "OpCode": "TGETB",
          "OpData": [ 14, 14, 3 ],
          "SourceLine": 23
        },
        {
          "OpCode": "GGET",
          "OpData": [ 15, 2 ],
          "SourceLine": 23
        },
        {
          "OpCode": "TGETB",
          "OpData": [ 15, 15, 4 ],
          "SourceLine": 23
        },
        {
          "OpCode": "CALL",
          "OpData": [ 0, 1, 13 ],
          "SourceLine": 23
        },
        {
          "OpCode": "RET0",
          "OpData": [ 0, 1 ],
          "SourceLine": 23
        }
      ],
      "Upvalues": [],
      "ObjectConstants": [
        {
          "Type": "FunctionPrototype",
          "Value": 0
        },
        {
          "Type": "String",
          "Value": "gettable"
        },
        {
          "Type": "String",
          "Value": "t"
        },
        {
          "Type": "String",
          "Value": "print"
        },
        {
          "Type": "String",
          "Value": "a0"
        },
        {
          "Type": "String",
          "Value": "a1"
        },
        {
          "Type": "String",
          "Value": "a2"
        },
        {
          "Type": "String",
          "Value": "a3"
        },
        {
          "Type": "String",
          "Value": "a4"
        },
        {
          "Type": "String",
          "Value": "a200"
        },
        {
          "Type": "String",
          "Value": "t2"
        }
      ],
      "NumberConstants": [
        {
          "Type": "Int32",
          "Value": 1
        }
      ]
    }
  ]
}
